{"MHGE":[{"len":5052,"wid":85,"surf":"ASP","lit":false,"closed":false,"le":{"id":"07","hdg":null,"lat":null,"lon":null},"he":{"id":"25","hdg":null,"lat":null,"lon":null}}],"MHLC":[{"len":9875,"wid":147,"surf":"ASP","lit":true,"closed":false,"le":{"id":"07","hdg":67.0,"lat":15.7372,"lon":-86.866},"he":{"id":"25","hdg":247.0,"lat":15.7478,"lon":-86.8401}}],"MHLM":[{"len":9203,"wid":148,"surf":"CON","lit":true,"closed":false,"le":{"id":"04","hdg":40.0,"lat":15.4423,"lon":-87.9326},"he":{"id":"22","hdg":220.0,"lat":15.4616,"lon":-87.9157}}],"MHNJ":[{"len":3990,"wid":66,"surf":"ASP","lit":false,"closed":false,"le":{"id":"12","hdg":115.2,"lat":16.4477,"lon":-85.9118},"he":{"id":"30","hdg":295.2,"lat":16.443,"lon":-85.9014}}],"MHRO":[{"len":7349,"wid":148,"surf":"ASP","lit":true,"closed":false,"le":{"id":"07","hdg":66.0,"lat":16.3126,"lon":-86.5325},"he":{"id":"25","hdg":246.0,"lat":16.3211,"lon":-86.5134}}],"MHSC":[{"len":8064,"wid":148,"surf":"ASP","lit":true,"closed":false,"le":{"id":"17","hdg":170.0,"lat":14.3932,"lon":-87.6232},"he":{"id":"35","hdg":350.0,"lat":14.3715,"lon":-87.6191}}],"MHTE":[{"len":4415,"wid":98,"surf":"ASP","lit":false,"closed":false,"le":{"id":"06","hdg":57.6,"lat":15.7726,"lon":-87.4811},"he":{"id":"24","hdg":237.6,"lat":15.7791,"lon":-87.4705}}],"MHTG":[{"len":6112,"wid":148,"surf":"ASP","lit":true,"closed":false,"le":{"id":"02","hdg":19.0,"lat":14.0529,"lon":-87.22},"he":{"id":"20","hdg":199.0,"lat":14.0688,"lon":-87.2144}}],"MHTJ":[{"len":3515,"wid":95,"surf":"ASP","lit":false,"closed":false,"le":{"id":"06","hdg":61.2,"lat":15.9245,"lon":-85.9426},"he":{"id":"24","hdg":241.2,"lat":15.9292,"lon":-85.9339}}]}