{"EVAD":{"lat":57.0986,"lon":24.2667,"elev":8,"region":"LV-011","runways":[{"len":null,"wid":null,"surf":"G","lit":false,"closed":false,"le":{"id":"15L","hdg":null,"lat":null,"lon":null},"he":{"id":"33R","hdg":null,"lat":null,"lon":null}},{"len":2130,"wid":null,"surf":"A","lit":false,"closed":false,"le":{"id":"15R","hdg":null,"lat":null,"lon":null},"he":{"id":"33L","hdg":null,"lat":null,"lon":null}}]},"EVAH":{"lat":57.4855,"lon":24.6724,"elev":211,"region":"LV-054","runways":[{"len":1250,"wid":50,"surf":"ASP","lit":false,"closed":false,"le":{"id":"17","hdg":null,"lat":null,"lon":null},"he":{"id":"35","hdg":null,"lat":null,"lon":null}}]},"EVAP":{"lat":56.666,"lon":23.7798,"elev":7,"region":"LV-JEL","runways":[]},"EVGA":{"lat":56.7783,"lon":24.8539,"elev":200,"region":"LV-067","runways":[{"len":8202,"wid":148,"surf":"ASP","lit":true,"closed":false,"le":{"id":"18","hdg":null,"lat":56.7902,"lon":24.8564},"he":{"id":"36","hdg":null,"lat":56.7679,"lon":24.8514}}]},"EVHB":{"lat":56.6079,"lon":23.4584,"elev":47,"region":"LV-041","runways":[]},"EVIA":{"lat":56.7381,"lon":21.3598,"elev":75,"region":"LV-112","runways":[]},"EVJC":{"lat":56.6063,"lon":23.4521,"elev":46,"region":"LV-041","runways":[]},"EVKA":{"lat":56.5347,"lon":25.8925,"elev":289,"region":"LV-042","runways":[{"len":2361,"wid":131,"surf":"CON","lit":false,"closed":false,"le":{"id":"07","hdg":null,"lat":null,"lon":null},"he":{"id":"25","hdg":null,"lat":null,"lon":null}}]},"EVLA":{"lat":56.5175,"lon":21.0969,"elev":16,"region":"LV-112","runways":[{"len":6568,"wid":131,"surf":"ASP","lit":true,"closed":false,"le":{"id":"06","hdg":70.0,"lat":56.5145,"lon":21.0818},"he":{"id":"24","hdg":250.0,"lat":56.5206,"lon":21.1124}}]},"EVLU":{"lat":56.5211,"lon":27.6941,"elev":null,"region":"LV-058","runways":[]},"EVPA":{"lat":56.8157,"lon":24.5243,"elev":64,"region":"LV-067","runways":[]},"EVRA":{"lat":56.9208,"lon":23.9707,"elev":36,"region":"LV-062","runways":[{"len":10499,"wid":148,"surf":"ASP","lit":true,"closed":false,"le":{"id":"18","hdg":185.0,"lat":56.9351,"lon":23.9731},"he":{"id":"36","hdg":5.0,"lat":56.9064,"lon":23.9683}}]},"EVRS":{"lat":56.9911,"lon":24.075,"elev":3,"region":"LV-RIX","runways":[{"len":3281,"wid":75,"surf":"ASP","lit":false,"closed":false,"le":{"id":"14","hdg":148.2,"lat":null,"lon":null},"he":{"id":"32","hdg":328.2,"lat":null,"lon":null}}]},"EVSM":{"lat":56.6641,"lon":24.9041,"elev":141,"region":"LV-067","runways":[]},"EVTA":{"lat":56.9422,"lon":23.2239,"elev":220,"region":"LV-099","runways":[{"len":8197,"wid":131,"surf":"ASP","lit":false,"closed":false,"le":{"id":"13","hdg":null,"lat":null,"lon":null},"he":{"id":"31","hdg":null,"lat":null,"lon":null}}]},"EVTE":{"lat":57.2544,"lon":22.5662,"elev":null,"region":"LV-097","runways":[{"len":1262,"wid":60,"surf":"ASP","lit":false,"closed":false,"le":{"id":"03","hdg":null,"lat":null,"lon":null},"he":{"id":"21","hdg":null,"lat":null,"lon":null}}]},"EVVA":{"lat":57.3578,"lon":21.5442,"elev":19,"region":"LV-VEN","runways":[{"len":4259,"wid":105,"surf":"PEM","lit":true,"closed":false,"le":{"id":"03","hdg":35.5,"lat":57.3531,"lon":21.5379},"he":{"id":"21","hdg":215.5,"lat":57.3625,"lon":21.5504}}]},"LT-0012":{"lat":56.8365,"lon":23.0207,"elev":null,"region":"LV-099","runways":[]},"LV-0001":{"lat":56.0434,"lon":26.3695,"elev":null,"region":"LV-111","runways":[]},"LV-0002":{"lat":55.89,"lon":26.46,"elev":305,"region":"LV-DGV","runways":[]},"LV-0003":{"lat":56.6922,"lon":22.4695,"elev":null,"region":"LV-088","runways":[]},"LV-0004":{"lat":56.8517,"lon":26.3126,"elev":null,"region":"LV-059","runways":[]},"LV-0005":{"lat":57.558,"lon":25.8376,"elev":null,"region":"LV-022","runways":[]},"LV-0006":{"lat":57.0454,"lon":24.946,"elev":371,"region":"LV-067","runways":[]},"LV-0007":{"lat":56.6834,"lon":21.9983,"elev":null,"region":"LV-050","runways":[]},"LV-0008":{"lat":57.2029,"lon":24.7535,"elev":null,"region":"LV-091","runways":[]},"LV-0009":{"lat":57.5586,"lon":25.4443,"elev":190,"region":"LV-113","runways":[]},"LV-0010":{"lat":56.7713,"lon":23.6551,"elev":null,"region":"LV-JEL","runways":[]},"LV-0011":{"lat":57.1694,"lon":25.6769,"elev":648,"region":"LV-022","runways":[]},"LV-0012":{"lat":56.4223,"lon":26.7287,"elev":null,"region":"LV-073","runways":[]},"LV-0013":{"lat":56.697,"lon":21.6293,"elev":230,"region":"LV-112","runways":[]},"LV-0014":{"lat":57.4407,"lon":25.8757,"elev":null,"region":"LV-094","runways":[{"len":1148,"wid":null,"surf":"G","lit":false,"closed":false,"le":{"id":"12","hdg":null,"lat":null,"lon":null},"he":{"id":"30","hdg":null,"lat":null,"lon":null}}]},"LV-0015":{"lat":56.7921,"lon":25.123,"elev":null,"region":"LV-067","runways":[]},"LV-0016":{"lat":57.6881,"lon":25.1666,"elev":null,"region":"LV-113","runways":[]},"LV-0017":{"lat":56.5157,"lon":26.258,"elev":null,"region":"LV-042","runways":[]},"LV-0018":{"lat":56.5082,"lon":24.0766,"elev":null,"region":"LV-016","runways":[]},"LV-0019":{"lat":57.7746,"lon":24.8871,"elev":null,"region":"LV-054","runways":[]},"LV-0020":{"lat":56.0367,"lon":26.7929,"elev":null,"region":"LV-111","runways":[]},"LV-0021":{"lat":56.5467,"lon":23.5342,"elev":null,"region":"LV-041","runways":[]},"LV-0022":{"lat":57.4406,"lon":22.5832,"elev":null,"region":"LV-097","runways":[]},"LV-0023":{"lat":56.7499,"lon":26.5977,"elev":null,"region":"LV-059","runways":[]},"LV-0024":{"lat":56.5664,"lon":27.3479,"elev":null,"region":"LV-077","runways":[]},"LV-0025":{"lat":57.7867,"lon":25.6035,"elev":null,"region":"LV-101","runways":[]},"LV-0026":{"lat":57.5325,"lon":22.6994,"elev":null,"region":"LV-097","runways":[]},"LV-0027":{"lat":56.676,"lon":23.3124,"elev":null,"region":"LV-026","runways":[]},"LV-0028":{"lat":56.7061,"lon":25.912,"elev":null,"region":"LV-059","runways":[]},"LV-0029":{"lat":57.3801,"lon":25.0111,"elev":null,"region":"LV-067","runways":[]},"LV-0030":{"lat":56.2733,"lon":26.035,"elev":null,"region":"LV-042","runways":[]},"LV-0031":{"lat":57.6476,"lon":24.3924,"elev":null,"region":"LV-054","runways":[]},"LV-0032":{"lat":56.3165,"lon":24.3327,"elev":null,"region":"LV-016","runways":[]},"LV-0033":{"lat":56.5923,"lon":26.9436,"elev":null,"region":"LV-077","runways":[]},"LV-0034":{"lat":56.4761,"lon":23.6995,"elev":null,"region":"LV-041","runways":[]},"LV-0035":{"lat":56.6813,"lon":23.464,"elev":null,"region":"LV-026","runways":[]},"LV-0036":{"lat":56.3515,"lon":26.3343,"elev":null,"region":"LV-056","runways":[]},"LV-0037":{"lat":57.1033,"lon":26.7332,"elev":null,"region":"LV-033","runways":[]},"LV-0038":{"lat":57.4994,"lon":22.4021,"elev":null,"region":"LV-097","runways":[]},"LV-0039":{"lat":56.6634,"lon":27.1765,"elev":null,"region":"LV-077","runways":[]},"LV-0040":{"lat":56.4297,"lon":21.5797,"elev":null,"region":"LV-112","runways":[]},"LV-0041":{"lat":56.8466,"lon":23.267,"elev":null,"region":"LV-099","runways":[]},"LV-0042":{"lat":56.9725,"lon":22.6337,"elev":null,"region":"LV-099","runways":[]},"LV-0043":{"lat":56.8547,"lon":22.2118,"elev":null,"region":"LV-050","runways":[]},"LV-0044":{"lat":56.9037,"lon":21.6393,"elev":null,"region":"LV-050","runways":[]},"LV-0045":{"lat":57.2668,"lon":22.8155,"elev":null,"region":"LV-097","runways":[]},"LV-0046":{"lat":56.4045,"lon":22.3372,"elev":null,"region":"LV-112","runways":[]},"LV-0047":{"lat":57.4684,"lon":27.5089,"elev":null,"region":"LV-007","runways":[]},"LV-0048":{"lat":56.2218,"lon":25.2995,"elev":null,"region":"LV-002","runways":[]},"LV-0049":{"lat":57.3295,"lon":25.3211,"elev":354,"region":"LV-022","runways":[]},"LV-0050":{"lat":56.422,"lon":23.9763,"elev":null,"region":"LV-016","runways":[]},"LV-0051":{"lat":56.8048,"lon":26.7709,"elev":null,"region":"LV-059","runways":[]},"LV-0052":{"lat":56.4047,"lon":25.7957,"elev":null,"region":"LV-042","runways":[]},"LV-0053":{"lat":56.9212,"lon":23.6414,"elev":null,"region":"LV-087","runways":[]},"LV-0054":{"lat":57.291,"lon":26.6184,"elev":309,"region":"LV-033","runways":[{"len":1674,"wid":66,"surf":"grass","lit":false,"closed":false,"le":{"id":"15","hdg":null,"lat":null,"lon":null},"he":{"id":"33","hdg":null,"lat":null,"lon":null}}]},"LV-1288":{"lat":56.8833,"lon":24.2267,"elev":26,"region":"LV-RIX","runways":[{"len":null,"wid":null,"surf":null,"lit":false,"closed":true,"le":{"id":"XX","hdg":null,"lat":null,"lon":null},"he":{"id":"XX","hdg":null,"lat":null,"lon":null}}]},"LV-7721":{"lat":57.3867,"lon":25.5083,"elev":256,"region":"LV-022","runways":[]},"LV-8037":{"lat":56.4749,"lon":23.1901,"elev":151,"region":"LV-041","runways":[]},"LV-8038":{"lat":56.6728,"lon":23.6792,"elev":20,"region":"LV-JEL","runways":[]},"LV-8039":{"lat":56.4058,"lon":21.8872,"elev":518,"region":"LV-112","runways":[]},"LV-8040":{"lat":55.9447,"lon":26.665,"elev":398,"region":"LV-111","runways":[{"len":8202,"wid":148,"surf":"Concrete","lit":true,"closed":false,"le":{"id":"02","hdg":null,"lat":null,"lon":null},"he":{"id":"20","hdg":null,"lat":null,"lon":null}}]},"LV-8041":{"lat":56.4132,"lon":23.3194,"elev":187,"region":"LV-026","runways":[]},"LV-8042":{"lat":56.5564,"lon":27.2128,"elev":null,"region":"LV-077","runways":[]},"LV-8043":{"lat":57.3238,"lon":25.3232,"elev":367,"region":"LV-022","runways":[]},"LV-8044":{"lat":56.6989,"lon":21.0625,"elev":null,"region":"LV-U-A","runways":[]},"LV-8045":{"lat":56.5392,"lon":21.0126,"elev":null,"region":"LV-LPX","runways":[]},"LV-8046":{"lat":56.3643,"lon":21.1483,"elev":null,"region":"LV-112","runways":[]},"LV-8047":{"lat":56.588,"lon":21.329,"elev":148,"region":"LV-112","runways":[{"len":1312,"wid":66,"surf":"ASP","lit":false,"closed":false,"le":{"id":"04","hdg":null,"lat":null,"lon":null},"he":{"id":"22","hdg":null,"lat":null,"lon":null}}]},"LV-8048":{"lat":57.1635,"lon":26.7705,"elev":null,"region":"LV-033","runways":[]},"LV-8049":{"lat":56.5018,"lon":20.9977,"elev":null,"region":"LV-LPX","runways":[]},"LV-8050":{"lat":57.8877,"lon":25.3338,"elev":null,"region":"LV-113","runways":[]}}