{"HRYG":{"lat":-1.6772,"lon":29.2589,"elev":5082,"region":"RW-04","runways":[{"len":3330,"wid":75,"surf":"ASP","lit":false,"closed":false,"le":{"id":"01","hdg":10.0,"lat":-1.6817,"lon":29.2581},"he":{"id":"19","hdg":190.0,"lat":-1.6727,"lon":29.2596}}]},"HRYI":{"lat":-2.5958,"lon":29.7367,"elev":5801,"region":"RW-05","runways":[{"len":4000,"wid":50,"surf":"ASP","lit":false,"closed":false,"le":{"id":"09","hdg":70.0,"lat":null,"lon":null},"he":{"id":"27","hdg":null,"lat":null,"lon":null}}]},"HRYN":{"lat":-2.3362,"lon":30.2067,"elev":4905,"region":"RW-02","runways":[]},"HRYO":{"lat":-1.55,"lon":30.383,"elev":4806,"region":"RW-02","runways":[]},"HRYR":{"lat":-1.9686,"lon":30.1395,"elev":4859,"region":"RW-01","runways":[{"len":11483,"wid":148,"surf":"ASP","lit":true,"closed":false,"le":{"id":"10","hdg":100.0,"lat":-1.9659,"lon":30.1239},"he":{"id":"28","hdg":280.0,"lat":-1.9713,"lon":30.155}}]},"HRYU":{"lat":-1.4969,"lon":29.6313,"elev":6102,"region":"RW-03","runways":[{"len":4000,"wid":100,"surf":"grass","lit":false,"closed":false,"le":{"id":"14","hdg":140.0,"lat":null,"lon":null},"he":{"id":"32","hdg":320.0,"lat":null,"lon":null}}]},"HRZA":{"lat":-2.4622,"lon":28.9079,"elev":5192,"region":"RW-04","runways":[{"len":4921,"wid":148,"surf":"ASP","lit":false,"closed":false,"le":{"id":"02","hdg":17.0,"lat":-2.4688,"lon":28.906},"he":{"id":"20","hdg":197.0,"lat":-2.4557,"lon":28.9099}}]},"RW-0001":{"lat":-2.2308,"lon":30.1809,"elev":4770,"region":"RW-02","runways":[]},"RW-0002":{"lat":-2.1444,"lon":30.1835,"elev":4630,"region":"RW-02","runways":[]}}