{"BTZ":{"lat":5.79,"lon":101.15,"elev":785,"region":"TH-95","runways":[{"len":5906,"wid":null,"surf":null,"lit":false,"closed":false,"le":{"id":null,"hdg":null,"lat":null,"lon":null},"he":{"id":null,"hdg":null,"lat":null,"lon":null}}]},"TH-0001":{"lat":12.9024,"lon":100.9332,"elev":160,"region":"TH-20","runways":[{"len":1500,"wid":null,"surf":"Grass","lit":false,"closed":false,"le":{"id":"01","hdg":null,"lat":null,"lon":null},"he":{"id":"19","hdg":null,"lat":null,"lon":null}}]},"TH-0002":{"lat":14.1706,"lon":100.6918,"elev":null,"region":"TH-13","runways":[]},"TH-0003":{"lat":14.1147,"lon":100.9495,"elev":15,"region":"TH-26","runways":[{"len":null,"wid":null,"surf":null,"lit":false,"closed":false,"le":{"id":"07","hdg":null,"lat":null,"lon":null},"he":{"id":"25","hdg":null,"lat":null,"lon":null}}]},"TH-0004":{"lat":14.1636,"lon":101.3371,"elev":null,"region":"TH-25","runways":[]},"TH-0005":{"lat":14.0366,"lon":100.6945,"elev":null,"region":"TH-13","runways":[]},"TH-0006":{"lat":13.9457,"lon":100.5744,"elev":10,"region":"TH-10","runways":[{"len":null,"wid":null,"surf":"Asphalt","lit":false,"closed":false,"le":{"id":"10","hdg":null,"lat":null,"lon":null},"he":{"id":"28","hdg":null,"lat":null,"lon":null}}]},"TH-0007":{"lat":12.6325,"lon":102.026,"elev":72,"region":"TH-22","runways":[]},"TH-0008":{"lat":11.7175,"lon":102.5203,"elev":20,"region":"TH-23","runways":[{"len":null,"wid":null,"surf":null,"lit":false,"closed":false,"le":{"id":"05","hdg":null,"lat":null,"lon":null},"he":{"id":"23","hdg":null,"lat":null,"lon":null}}]},"TH-0009":{"lat":12.836,"lon":102.1688,"elev":null,"region":"TH-22","runways":[]},"TH-0010":{"lat":12.7099,"lon":101.6305,"elev":null,"region":"TH-21","runways":[]},"TH-0011":{"lat":13.1403,"lon":101.0464,"elev":214,"region":"TH-20","runways":[{"len":2200,"wid":null,"surf":"Asphalt","lit":false,"closed":false,"le":{"id":"06","hdg":null,"lat":null,"lon":null},"he":{"id":"24","hdg":null,"lat":null,"lon":null}}]},"TH-0012":{"lat":13.236,"lon":100.9949,"elev":null,"region":"TH-20","runways":[]},"TH-0013":{"lat":13.3938,"lon":101.3205,"elev":null,"region":"TH-20","runways":[]},"TH-0014":{"lat":13.8578,"lon":100.3249,"elev":null,"region":"TH-12","runways":[]},"TH-0015":{"lat":13.5402,"lon":100.3294,"elev":null,"region":"TH-74","runways":[{"len":2600,"wid":null,"surf":"asphalt","lit":false,"closed":false,"le":{"id":"16","hdg":null,"lat":null,"lon":null},"he":{"id":"34","hdg":null,"lat":null,"lon":null}}]},"TH-0016":{"lat":13.5738,"lon":99.753,"elev":null,"region":"TH-70","runways":[]},"TH-0017":{"lat":12.8717,"lon":99.7926,"elev":null,"region":"TH-67","runways":[]},"TH-0018":{"lat":12.3896,"lon":99.958,"elev":null,"region":"TH-77","runways":[]},"TH-0019":{"lat":7.1349,"lon":100.3306,"elev":null,"region":"TH-90","runways":[]},"TH-0020":{"lat":6.8341,"lon":101.0221,"elev":null,"region":"TH-90","runways":[]},"TH-0021":{"lat":13.7553,"lon":101.395,"elev":166,"region":"TH-24","runways":[]},"TH-0022":{"lat":5.7816,"lon":101.1593,"elev":null,"region":"TH-95","runways":[]},"TH-0023":{"lat":13.1442,"lon":101.1061,"elev":null,"region":"TH-20","runways":[{"len":null,"wid":null,"surf":null,"lit":false,"closed":false,"le":{"id":"03","hdg":null,"lat":null,"lon":null},"he":{"id":"21","hdg":null,"lat":null,"lon":null}}]},"TH-0024":{"lat":13.945,"lon":102.0043,"elev":null,"region":"TH-27","runways":[{"len":null,"wid":null,"surf":"Grass","lit":false,"closed":false,"le":{"id":"18","hdg":null,"lat":null,"lon":null},"he":{"id":"36","hdg":null,"lat":null,"lon":null}}]},"TH-0025":{"lat":12.6714,"lon":101.5476,"elev":null,"region":"TH-21","runways":[{"len":2296,"wid":65,"surf":"asphalt","lit":false,"closed":false,"le":{"id":"17","hdg":null,"lat":null,"lon":null},"he":{"id":"35","hdg":null,"lat":null,"lon":null}}]},"TH-0026":{"lat":12.8932,"lon":100.9601,"elev":null,"region":"TH-20","runways":[]},"TH-0027":{"lat":18.6761,"lon":99.1052,"elev":990,"region":"TH-50","runways":[]},"TH-0028":{"lat":13.091,"lon":100.9675,"elev":84,"region":"TH-20","runways":[{"len":3773,"wid":82,"surf":"Tarmac","lit":false,"closed":false,"le":{"id":"05","hdg":null,"lat":null,"lon":null},"he":{"id":"23","hdg":null,"lat":null,"lon":null}}]},"TH-0029":{"lat":16.7732,"lon":104.0337,"elev":null,"region":"TH-46","runways":[]},"TH-0030":{"lat":16.1596,"lon":104.5932,"elev":null,"region":"TH-35","runways":[{"len":4921,"wid":null,"surf":"Asphalt","lit":false,"closed":true,"le":{"id":"03","hdg":null,"lat":null,"lon":null},"he":{"id":"21","hdg":null,"lat":null,"lon":null}}]},"TH-0031":{"lat":9.7411,"lon":100.0707,"elev":900,"region":"TH-84","runways":[{"len":3609,"wid":null,"surf":"ASP","lit":false,"closed":true,"le":{"id":null,"hdg":null,"lat":null,"lon":null},"he":{"id":null,"hdg":null,"lat":null,"lon":null}}]},"TH-0032":{"lat":12.8351,"lon":100.9812,"elev":null,"region":"TH-20","runways":[]},"TH-0034":{"lat":14.0805,"lon":100.8526,"elev":20,"region":"TH-13","runways":[{"len":2690,"wid":75,"surf":"Asphalt","lit":false,"closed":false,"le":{"id":"09","hdg":90.0,"lat":null,"lon":null},"he":{"id":"27","hdg":270.0,"lat":null,"lon":null}}]},"TH-0035":{"lat":14.1172,"lon":100.7617,"elev":null,"region":"TH-13","runways":[]},"TH-0036":{"lat":14.0214,"lon":101.703,"elev":41,"region":"TH-25","runways":[{"len":4320,"wid":164,"surf":null,"lit":false,"closed":false,"le":{"id":"02","hdg":null,"lat":14.016,"lon":101.7008},"he":{"id":"20","hdg":null,"lat":14.027,"lon":101.7054}}]},"TH-0037":{"lat":14.1252,"lon":99.447,"elev":null,"region":"TH-71","runways":[]},"TH-0038":{"lat":14.0645,"lon":99.3617,"elev":null,"region":"TH-71","runways":[]},"TH-0039":{"lat":13.777,"lon":101.6135,"elev":null,"region":"TH-25","runways":[]},"TH-0040":{"lat":14.6312,"lon":101.4659,"elev":null,"region":"TH-30","runways":[{"len":2340,"wid":60,"surf":"asphalt","lit":false,"closed":false,"le":{"id":"10","hdg":null,"lat":null,"lon":null},"he":{"id":"28","hdg":null,"lat":null,"lon":null}}]},"TH-0041":{"lat":8.0779,"lon":98.3017,"elev":null,"region":"TH-83","runways":[]},"TH-0042":{"lat":18.704,"lon":99.1192,"elev":1020,"region":"TH-50","runways":[{"len":null,"wid":null,"surf":"Asphalt","lit":false,"closed":false,"le":{"id":"12","hdg":null,"lat":null,"lon":null},"he":{"id":"30","hdg":null,"lat":null,"lon":null}}]},"TH-0043":{"lat":17.522,"lon":103.5512,"elev":554,"region":"TH-47","runways":[{"len":2400,"wid":60,"surf":"Grass","lit":false,"closed":false,"le":{"id":"07","hdg":null,"lat":null,"lon":null},"he":{"id":"25","hdg":null,"lat":null,"lon":null}}]},"TH-0044":{"lat":14.7712,"lon":100.776,"elev":164,"region":"TH-19","runways":[{"len":2290,"wid":60,"surf":"grass","lit":false,"closed":false,"le":{"id":"03","hdg":null,"lat":null,"lon":null},"he":{"id":"21","hdg":null,"lat":null,"lon":null}}]},"TH-0045":{"lat":12.9207,"lon":101.1836,"elev":186,"region":"TH-21","runways":[]},"TH-0046":{"lat":14.1195,"lon":100.621,"elev":16,"region":"TH-13","runways":[]},"TH-0047":{"lat":13.8604,"lon":100.6339,"elev":23,"region":"TH-10","runways":[]},"TH-0048":{"lat":13.7385,"lon":100.5376,"elev":null,"region":"TH-10","runways":[]},"TH-0049":{"lat":13.2892,"lon":100.9632,"elev":null,"region":"TH-20","runways":[]},"TH-0050":{"lat":12.8551,"lon":100.9909,"elev":230,"region":"TH-20","runways":[{"len":null,"wid":null,"surf":null,"lit":false,"closed":false,"le":{"id":"01","hdg":null,"lat":null,"lon":null},"he":{"id":"19","hdg":null,"lat":null,"lon":null}}]},"TH-0051":{"lat":19.8854,"lon":99.8268,"elev":1312,"region":"TH-57","runways":[{"len":5065,"wid":103,"surf":"ASP","lit":true,"closed":false,"le":{"id":"18","hdg":182.0,"lat":19.8927,"lon":99.8271},"he":{"id":"36","hdg":2.0,"lat":19.8788,"lon":99.8266}}]},"TH-0052":{"lat":12.8325,"lon":100.9494,"elev":100,"region":"TH-20","runways":[]},"TH-0053":{"lat":17.4872,"lon":101.7208,"elev":null,"region":"TH-42","runways":[]},"TH-0054":{"lat":17.6265,"lon":100.0923,"elev":null,"region":"TH-53","runways":[]},"TH-0055":{"lat":8.4165,"lon":100.0012,"elev":null,"region":"TH-80","runways":[]},"TH-0056":{"lat":18.3559,"lon":99.407,"elev":null,"region":"TH-52","runways":[]},"TH-0057":{"lat":18.1991,"lon":99.4131,"elev":null,"region":"TH-52","runways":[]},"TH-0058":{"lat":18.4125,"lon":99.7283,"elev":null,"region":"TH-52","runways":[]},"TH-0059":{"lat":19.294,"lon":100.8573,"elev":null,"region":"TH-55","runways":[]},"TH-0060":{"lat":18.6656,"lon":100.767,"elev":null,"region":"TH-55","runways":[]},"TH-0061":{"lat":12.8354,"lon":100.9253,"elev":null,"region":"TH-20","runways":[]},"TH-0062":{"lat":14.2769,"lon":100.6478,"elev":null,"region":"TH-14","runways":[{"len":1824,"wid":null,"surf":"Asphalt","lit":false,"closed":false,"le":{"id":"18","hdg":null,"lat":null,"lon":null},"he":{"id":"36","hdg":null,"lat":null,"lon":null}}]},"TH-0063":{"lat":14.696,"lon":101.4911,"elev":1047,"region":"TH-30","runways":[]},"TH-0064":{"lat":14.9543,"lon":102.0739,"elev":643,"region":"TH-30","runways":[{"len":null,"wid":null,"surf":"Concrete","lit":false,"closed":false,"le":{"id":"07","hdg":null,"lat":null,"lon":null},"he":{"id":"25","hdg":null,"lat":null,"lon":null}}]},"TH-0065":{"lat":14.1139,"lon":99.663,"elev":108,"region":"TH-30","runways":[]},"TH-0066":{"lat":13.7721,"lon":100.5438,"elev":22,"region":"TH-10","runways":[]},"VN-0020":{"lat":14.1099,"lon":101.0017,"elev":6,"region":"TH-26","runways":[]},"VTBD":{"lat":13.9126,"lon":100.607,"elev":9,"region":"TH-10","runways":[{"len":12139,"wid":197,"surf":"ASP","lit":true,"closed":false,"le":{"id":"03L","hdg":29.0,"lat":13.8971,"lon":100.596},"he":{"id":"21R","hdg":209.0,"lat":13.9264,"lon":100.612}},{"len":11483,"wid":148,"surf":"ASP","lit":true,"closed":false,"le":{"id":"03R","hdg":29.0,"lat":13.8995,"lon":100.602},"he":{"id":"21L","hdg":209.0,"lat":13.9274,"lon":100.617}}]},"VTBE":{"lat":14.5082,"lon":100.919,"elev":46,"region":"TH-19","runways":[{"len":null,"wid":null,"surf":"concrete","lit":false,"closed":false,"le":{"id":"H1","hdg":null,"lat":null,"lon":null},"he":{"id":"H1","hdg":null,"lat":null,"lon":null}}]},"VTBH":{"lat":14.9494,"lon":100.643,"elev":95,"region":"TH-16","runways":[{"len":3300,"wid":98,"surf":"ASP","lit":true,"closed":false,"le":{"id":"01","hdg":9.0,"lat":14.9449,"lon":100.642},"he":{"id":"19","hdg":189.0,"lat":14.9539,"lon":100.644}},{"len":3890,"wid":98,"surf":"ASP","lit":true,"closed":false,"le":{"id":"06","hdg":58.0,"lat":14.9458,"lon":100.637},"he":{"id":"24","hdg":238.0,"lat":14.9514,"lon":100.646}}]},"VTBI":{"lat":14.0778,"lon":101.38,"elev":80,"region":"TH-25","runways":[{"len":3280,"wid":112,"surf":"ASP","lit":false,"closed":false,"le":{"id":"17","hdg":172.3,"lat":14.0822,"lon":101.379},"he":{"id":"35","hdg":352.3,"lat":14.0733,"lon":101.381}}]},"VTBK":{"lat":14.102,"lon":99.9172,"elev":30,"region":"TH-72","runways":[{"len":9000,"wid":148,"surf":"CON","lit":true,"closed":false,"le":{"id":"03","hdg":30.0,"lat":14.0912,"lon":99.9109},"he":{"id":"21","hdg":210.0,"lat":14.1128,"lon":99.9235}}]},"VTBL":{"lat":14.8746,"lon":100.6634,"elev":123,"region":"TH-16","runways":[{"len":4435,"wid":148,"surf":"CON","lit":true,"closed":false,"le":{"id":"05","hdg":46.8,"lat":14.8694,"lon":100.658},"he":{"id":"23","hdg":226.8,"lat":14.8777,"lon":100.667}},{"len":600,"wid":64,"surf":"ASP","lit":false,"closed":false,"le":{"id":"10","hdg":96.0,"lat":14.8863,"lon":100.661},"he":{"id":"28","hdg":276.0,"lat":14.8862,"lon":100.663}},{"len":7252,"wid":148,"surf":"ASP","lit":true,"closed":false,"le":{"id":"16","hdg":160.3,"lat":14.8839,"lon":100.66},"he":{"id":"34","hdg":340.3,"lat":14.8651,"lon":100.667}}]},"VTBN":{"lat":12.4172,"lon":99.8694,"elev":null,"region":"TH-77","runways":[]},"VTBO":{"lat":12.2746,"lon":102.319,"elev":105,"region":"TH-23","runways":[{"len":5899,"wid":150,"surf":"ASP","lit":true,"closed":false,"le":{"id":"05","hdg":51.0,"lat":12.2703,"lon":102.314},"he":{"id":"23","hdg":231.0,"lat":12.2789,"lon":102.324}}]},"VTBP":{"lat":11.7884,"lon":99.8047,"elev":10,"region":"TH-77","runways":[{"len":6562,"wid":131,"surf":"ASP","lit":true,"closed":false,"le":{"id":"08","hdg":77.6,"lat":11.7852,"lon":99.7899},"he":{"id":"26","hdg":257.6,"lat":11.7891,"lon":99.8079}},{"len":3281,"wid":131,"surf":"ASP","lit":false,"closed":false,"le":{"id":"18","hdg":179.0,"lat":11.7931,"lon":99.8046},"he":{"id":"36","hdg":359.0,"lat":11.7841,"lon":99.8047}}]},"VTBS":{"lat":13.6811,"lon":100.747,"elev":5,"region":"TH-10","runways":[{"len":13123,"wid":197,"surf":"ASP","lit":true,"closed":false,"le":{"id":"01","hdg":14.0,"lat":13.6567,"lon":100.7518},"he":{"id":"19","hdg":194.0,"lat":13.6917,"lon":100.761}},{"len":13123,"wid":197,"surf":"ASP","lit":true,"closed":false,"le":{"id":"02L","hdg":14.0,"lat":13.6652,"lon":100.7292},"he":{"id":"20R","hdg":194.0,"lat":13.7002,"lon":100.7384}},{"len":12139,"wid":197,"surf":"ASP","lit":true,"closed":false,"le":{"id":"02R","hdg":14.0,"lat":13.6713,"lon":100.7347},"he":{"id":"20L","hdg":194.0,"lat":13.7037,"lon":100.7432}}]},"VTBT":{"lat":13.2324,"lon":100.9568,"elev":90,"region":"TH-20","runways":[{"len":3031,"wid":null,"surf":"ASP","lit":false,"closed":false,"le":{"id":"05","hdg":null,"lat":null,"lon":null},"he":{"id":"23","hdg":null,"lat":null,"lon":null}}]},"VTBU":{"lat":12.6799,"lon":101.005,"elev":42,"region":"TH-21","runways":[{"len":11500,"wid":197,"surf":"ASP","lit":true,"closed":false,"le":{"id":"18","hdg":185.0,"lat":12.6958,"lon":101.006},"he":{"id":"36","hdg":5.0,"lat":12.6641,"lon":101.004}}]},"VTBV":{"lat":12.254,"lon":102.5185,"elev":-1,"region":"TH-23","runways":[{"len":3000,"wid":50,"surf":"concrete","lit":true,"closed":false,"le":{"id":"16","hdg":null,"lat":12.2539,"lon":102.5152},"he":{"id":"34","hdg":null,"lat":12.2461,"lon":102.5181}}]},"VTBW":{"lat":13.7692,"lon":102.316,"elev":200,"region":"TH-27","runways":[{"len":4922,"wid":115,"surf":"ASP","lit":false,"closed":false,"le":{"id":"05","hdg":50.0,"lat":13.7644,"lon":102.31},"he":{"id":"23","hdg":230.0,"lat":13.7732,"lon":102.321}}]},"VTCB":{"lat":19.5,"lon":100.283,"elev":1272,"region":"TH-56","runways":[]},"VTCC":{"lat":18.7668,"lon":98.9626,"elev":1036,"region":"TH-50","runways":[{"len":11155,"wid":148,"surf":"ASP","lit":true,"closed":false,"le":{"id":"18","hdg":180.0,"lat":18.7838,"lon":98.9629},"he":{"id":"36","hdg":null,"lat":18.753,"lon":98.9629}}]},"VTCH":{"lat":19.3013,"lon":97.9758,"elev":929,"region":"TH-58","runways":[{"len":6562,"wid":98,"surf":"ASP","lit":true,"closed":false,"le":{"id":"11","hdg":107.0,"lat":19.304,"lon":97.9668},"he":{"id":"29","hdg":287.0,"lat":19.2985,"lon":97.9849}}]},"VTCI":{"lat":19.3721,"lon":98.4359,"elev":1676,"region":"TH-58","runways":[{"len":2329,"wid":59,"surf":"ASP","lit":false,"closed":false,"le":{"id":"01","hdg":null,"lat":19.3696,"lon":98.4352},"he":{"id":"19","hdg":null,"lat":19.3751,"lon":98.4368}}]},"VTCL":{"lat":18.2709,"lon":99.5042,"elev":811,"region":"TH-52","runways":[{"len":6465,"wid":95,"surf":"ASP","lit":true,"closed":false,"le":{"id":"18","hdg":175.4,"lat":18.2798,"lon":99.5035},"he":{"id":"36","hdg":355.4,"lat":18.262,"lon":99.505}}]},"VTCN":{"lat":18.8079,"lon":100.783,"elev":685,"region":"TH-55","runways":[{"len":6562,"wid":148,"surf":"ASP","lit":true,"closed":false,"le":{"id":"02","hdg":20.7,"lat":18.7995,"lon":100.78},"he":{"id":"20","hdg":200.7,"lat":18.8163,"lon":100.787}}]},"VTCO":{"lat":18.549,"lon":99.0124,"elev":925,"region":"TH-51","runways":[]},"VTCP":{"lat":18.1322,"lon":100.165,"elev":538,"region":"TH-54","runways":[{"len":4921,"wid":98,"surf":"ASP","lit":true,"closed":false,"le":{"id":"01","hdg":6.0,"lat":18.1254,"lon":100.164},"he":{"id":"19","hdg":186.0,"lat":18.1389,"lon":100.165}}]},"VTCS":{"lat":18.181,"lon":97.9306,"elev":750,"region":"TH-58","runways":[{"len":2400,"wid":null,"surf":"Asphalt","lit":false,"closed":false,"le":{"id":"01","hdg":null,"lat":null,"lon":null},"he":{"id":"19","hdg":null,"lat":null,"lon":null}}]},"VTCT":{"lat":19.9523,"lon":99.8829,"elev":1280,"region":"TH-57","runways":[{"len":9843,"wid":148,"surf":"ASP","lit":true,"closed":false,"le":{"id":"03","hdg":29.0,"lat":19.9405,"lon":99.876},"he":{"id":"21","hdg":209.0,"lat":19.9642,"lon":99.8899}}]},"VTCY":{"lat":18.6762,"lon":99.1116,"elev":983,"region":"TH-50","runways":[{"len":null,"wid":null,"surf":null,"lit":false,"closed":false,"le":{"id":"16","hdg":null,"lat":null,"lon":null},"he":{"id":"34","hdg":null,"lat":null,"lon":null}}]},"VTED":{"lat":17.383,"lon":102.8,"elev":591,"region":"TH-41","runways":[]},"VTPB":{"lat":16.676,"lon":101.195,"elev":450,"region":"TH-67","runways":[{"len":6890,"wid":148,"surf":"ASP","lit":true,"closed":false,"le":{"id":"18","hdg":180.0,"lat":16.6855,"lon":101.195},"he":{"id":"36","hdg":360.0,"lat":16.6665,"lon":101.195}}]},"VTPH":{"lat":12.6362,"lon":99.9515,"elev":62,"region":"TH-76","runways":[{"len":6890,"wid":115,"surf":"ASP","lit":true,"closed":false,"le":{"id":"16","hdg":159.7,"lat":12.6451,"lon":99.9482},"he":{"id":"34","hdg":339.7,"lat":12.6273,"lon":99.9549}}]},"VTPI":{"lat":15.2773,"lon":100.296,"elev":107,"region":"TH-60","runways":[{"len":9843,"wid":148,"surf":"CON","lit":true,"closed":false,"le":{"id":"18","hdg":181.3,"lat":15.2909,"lon":100.296},"he":{"id":"36","hdg":1.3,"lat":15.2637,"lon":100.296}}]},"VTPL":{"lat":16.8241,"lon":101.2512,"elev":500,"region":"TH-67","runways":[{"len":3281,"wid":98,"surf":"ASP","lit":false,"closed":false,"le":{"id":"01","hdg":7.9,"lat":16.8199,"lon":101.251},"he":{"id":"19","hdg":187.9,"lat":16.8288,"lon":101.252}}]},"VTPM":{"lat":16.6999,"lon":98.5451,"elev":690,"region":"TH-63","runways":[{"len":4921,"wid":98,"surf":"ASP","lit":true,"closed":false,"le":{"id":"09","hdg":89.1,"lat":16.6998,"lon":98.538},"he":{"id":"27","hdg":269.1,"lat":16.7,"lon":98.5521}}]},"VTPN":{"lat":15.673,"lon":100.137,"elev":113,"region":"TH-60","runways":[{"len":4481,"wid":98,"surf":"ASP","lit":true,"closed":false,"le":{"id":"05","hdg":53.1,"lat":15.6693,"lon":100.132},"he":{"id":"23","hdg":233.1,"lat":15.6767,"lon":100.142}}]},"VTPO":{"lat":17.238,"lon":99.8182,"elev":179,"region":"TH-64","runways":[{"len":6890,"wid":148,"surf":"ASP","lit":true,"closed":false,"le":{"id":"18","hdg":181.0,"lat":17.2475,"lon":99.8184},"he":{"id":"36","hdg":1.0,"lat":17.2285,"lon":99.818}}]},"VTPP":{"lat":16.7829,"lon":100.279,"elev":154,"region":"TH-65","runways":[{"len":9843,"wid":148,"surf":"ASP","lit":true,"closed":false,"le":{"id":"14","hdg":144.0,"lat":16.7939,"lon":100.271},"he":{"id":"32","hdg":324.0,"lat":16.772,"lon":100.287}}]},"VTPR":{"lat":13.6686,"lon":99.7314,"elev":88,"region":"TH-70","runways":[]},"VTPT":{"lat":16.896,"lon":99.2533,"elev":478,"region":"TH-63","runways":[{"len":4921,"wid":98,"surf":"ASP","lit":true,"closed":false,"le":{"id":"09","hdg":90.3,"lat":16.896,"lon":99.2463},"he":{"id":"27","hdg":270.3,"lat":16.896,"lon":99.2604}}]},"VTPU":{"lat":17.6737,"lon":100.2353,"elev":262,"region":"TH-53","runways":[]},"VTPY":{"lat":17.2342,"lon":99.0579,"elev":492,"region":"TH-63","runways":[{"len":4899,"wid":98,"surf":"ASP","lit":false,"closed":false,"le":{"id":"05","hdg":47.5,"lat":17.2296,"lon":99.0527},"he":{"id":"23","hdg":227.5,"lat":17.2388,"lon":99.0631}}]},"VTSA":{"lat":6.6614,"lon":100.08,"elev":18,"region":"TH-91","runways":[{"len":3609,"wid":131,"surf":"ASP","lit":false,"closed":false,"le":{"id":"17","hdg":173.8,"lat":6.6664,"lon":100.08},"he":{"id":"35","hdg":353.8,"lat":6.6564,"lon":100.081}}]},"VTSB":{"lat":9.1326,"lon":99.1356,"elev":20,"region":"TH-84","runways":[{"len":9843,"wid":148,"surf":"ASP","lit":true,"closed":false,"le":{"id":"04","hdg":44.2,"lat":9.1228,"lon":99.126},"he":{"id":"22","hdg":224.2,"lat":9.1424,"lon":99.1451}}]},"VTSC":{"lat":6.5199,"lon":101.743,"elev":16,"region":"TH-96","runways":[{"len":8202,"wid":148,"surf":"ASP","lit":true,"closed":false,"le":{"id":"02","hdg":23.0,"lat":6.5116,"lon":101.74},"he":{"id":"20","hdg":203.0,"lat":6.5282,"lon":101.747}}]},"VTSE":{"lat":10.7112,"lon":99.3617,"elev":18,"region":"TH-86","runways":[{"len":6890,"wid":148,"surf":"ASP","lit":true,"closed":false,"le":{"id":"06","hdg":60.1,"lat":10.7065,"lon":99.3534},"he":{"id":"24","hdg":240.1,"lat":10.7159,"lon":99.37}}]},"VTSF":{"lat":8.5396,"lon":99.9447,"elev":13,"region":"TH-80","runways":[{"len":6890,"wid":148,"surf":"ASP","lit":true,"closed":false,"le":{"id":"01","hdg":6.0,"lat":8.5301,"lon":99.9437},"he":{"id":"19","hdg":186.0,"lat":8.5491,"lon":99.9457}}]},"VTSG":{"lat":8.0956,"lon":98.989,"elev":82,"region":"TH-81","runways":[{"len":9842,"wid":148,"surf":"ASP","lit":true,"closed":false,"le":{"id":"14","hdg":140.6,"lat":8.1065,"lon":98.9801},"he":{"id":"32","hdg":320.6,"lat":8.0918,"lon":98.9922}}]},"VTSH":{"lat":7.1866,"lon":100.608,"elev":12,"region":"TH-90","runways":[{"len":4954,"wid":148,"surf":"ASP","lit":true,"closed":false,"le":{"id":"13","hdg":134.8,"lat":7.1913,"lon":100.603},"he":{"id":"31","hdg":314.8,"lat":7.1817,"lon":100.613}}]},"VTSK":{"lat":6.7855,"lon":101.154,"elev":8,"region":"TH-94","runways":[{"len":4593,"wid":131,"surf":"ASP","lit":false,"closed":false,"le":{"id":"08","hdg":86.0,"lat":6.785,"lon":101.147},"he":{"id":"26","hdg":266.0,"lat":6.7859,"lon":101.16}}]},"VTSM":{"lat":9.5478,"lon":100.062,"elev":64,"region":"TH-84","runways":[{"len":6759,"wid":148,"surf":"ASP","lit":true,"closed":false,"le":{"id":"17","hdg":174.5,"lat":9.5572,"lon":100.062},"he":{"id":"35","hdg":354.5,"lat":9.5387,"lon":100.063}}]},"VTSN":{"lat":8.4711,"lon":99.9556,"elev":44,"region":"TH-80","runways":[{"len":7546,"wid":148,"surf":"ASP","lit":false,"closed":false,"le":{"id":"18","hdg":173.0,"lat":8.4815,"lon":99.9544},"he":{"id":"36","hdg":353.0,"lat":8.4608,"lon":99.9569}}]},"VTSP":{"lat":8.1133,"lon":98.3174,"elev":82,"region":"TH-83","runways":[{"len":10171,"wid":148,"surf":"ASP","lit":true,"closed":false,"le":{"id":"09","hdg":85.0,"lat":8.112,"lon":98.3033},"he":{"id":"27","hdg":265.0,"lat":8.1145,"lon":98.3304}}]},"VTSR":{"lat":9.7776,"lon":98.5855,"elev":57,"region":"TH-85","runways":[{"len":6562,"wid":148,"surf":"CON","lit":true,"closed":false,"le":{"id":"02","hdg":24.0,"lat":9.7693,"lon":98.5818},"he":{"id":"20","hdg":204.0,"lat":9.7859,"lon":98.5892}}]},"VTSS":{"lat":6.9332,"lon":100.393,"elev":90,"region":"TH-90","runways":[{"len":10007,"wid":148,"surf":"ASP","lit":true,"closed":false,"le":{"id":"08","hdg":83.0,"lat":6.9308,"lon":100.379},"he":{"id":"26","hdg":263.0,"lat":6.9342,"lon":100.407}}]},"VTST":{"lat":7.5087,"lon":99.6166,"elev":67,"region":"TH-92","runways":[{"len":6890,"wid":148,"surf":"ASP","lit":true,"closed":false,"le":{"id":"08","hdg":80.9,"lat":7.5072,"lon":99.6072},"he":{"id":"26","hdg":260.9,"lat":7.5103,"lon":99.626}}]},"VTSW":{"lat":8.0187,"lon":98.4029,"elev":20,"region":"TH-83","runways":[{"len":1640,"wid":59,"surf":"Grass","lit":false,"closed":false,"le":{"id":"13","hdg":null,"lat":null,"lon":null},"he":{"id":"31","hdg":null,"lat":null,"lon":null}}]},"VTUD":{"lat":17.3862,"lon":102.7886,"elev":579,"region":"TH-41","runways":[{"len":10000,"wid":148,"surf":"ASP","lit":true,"closed":false,"le":{"id":"12","hdg":117.0,"lat":17.3927,"lon":102.775},"he":{"id":"30","hdg":297.0,"lat":17.3802,"lon":102.801}}]},"VTUI":{"lat":17.1951,"lon":104.119,"elev":529,"region":"TH-47","runways":[{"len":8530,"wid":148,"surf":"ASP","lit":true,"closed":false,"le":{"id":"05","hdg":45.0,"lat":17.1868,"lon":104.11},"he":{"id":"23","hdg":225.0,"lat":17.2035,"lon":104.127}}]},"VTUJ":{"lat":14.8683,"lon":103.498,"elev":478,"region":"TH-32","runways":[{"len":5053,"wid":115,"surf":"ASP","lit":false,"closed":false,"le":{"id":"01","hdg":7.5,"lat":14.8614,"lon":103.497},"he":{"id":"19","hdg":187.5,"lat":14.8752,"lon":103.499}}]},"VTUK":{"lat":16.4666,"lon":102.784,"elev":670,"region":"TH-40","runways":[{"len":10007,"wid":148,"surf":"ASP","lit":true,"closed":false,"le":{"id":"03","hdg":32.9,"lat":16.455,"lon":102.776},"he":{"id":"21","hdg":212.9,"lat":16.4782,"lon":102.791}}]},"VTUL":{"lat":17.4391,"lon":101.722,"elev":860,"region":"TH-42","runways":[{"len":6890,"wid":148,"surf":"ASP","lit":true,"closed":false,"le":{"id":"01","hdg":16.8,"lat":17.43,"lon":101.719},"he":{"id":"19","hdg":196.8,"lat":17.4482,"lon":101.725}}]},"VTUN":{"lat":14.9347,"lon":102.0789,"elev":729,"region":"TH-30","runways":[{"len":9843,"wid":148,"surf":"CON","lit":true,"closed":false,"le":{"id":"06","hdg":62.1,"lat":14.9281,"lon":102.066},"he":{"id":"24","hdg":242.1,"lat":14.9408,"lon":102.091}}]},"VTUO":{"lat":15.2295,"lon":103.253,"elev":590,"region":"TH-31","runways":[{"len":6890,"wid":148,"surf":"ASP","lit":true,"closed":false,"le":{"id":"04","hdg":35.1,"lat":15.2218,"lon":103.248},"he":{"id":"22","hdg":215.1,"lat":15.2373,"lon":103.259}}]},"VTUQ":{"lat":14.9495,"lon":102.313,"elev":765,"region":"TH-30","runways":[{"len":6890,"wid":148,"surf":"ASP","lit":true,"closed":false,"le":{"id":"06","hdg":61.3,"lat":14.9449,"lon":102.304},"he":{"id":"24","hdg":241.3,"lat":14.9541,"lon":102.321}}]},"VTUR":{"lat":16.0704,"lon":103.646,"elev":459,"region":"TH-45","runways":[{"len":3125,"wid":98,"surf":"ASP","lit":false,"closed":false,"le":{"id":"17","hdg":166.6,"lat":16.0745,"lon":103.645},"he":{"id":"35","hdg":346.6,"lat":16.0662,"lon":103.647}}]},"VTUU":{"lat":15.2513,"lon":104.87,"elev":406,"region":"TH-34","runways":[{"len":9848,"wid":148,"surf":"ASP","lit":true,"closed":false,"le":{"id":"05","hdg":51.5,"lat":15.2428,"lon":104.859},"he":{"id":"23","hdg":231.5,"lat":15.2597,"lon":104.881}}]},"VTUV":{"lat":16.1168,"lon":103.774,"elev":451,"region":"TH-45","runways":[{"len":6890,"wid":148,"surf":"ASP","lit":true,"closed":false,"le":{"id":"18","hdg":182.5,"lat":16.1263,"lon":103.774},"he":{"id":"36","hdg":2.5,"lat":16.1073,"lon":103.773}}]},"VTUW":{"lat":17.3838,"lon":104.643,"elev":587,"region":"TH-48","runways":[{"len":8203,"wid":148,"surf":"ASP","lit":true,"closed":false,"le":{"id":"15","hdg":144.8,"lat":17.393,"lon":104.636},"he":{"id":"33","hdg":324.8,"lat":17.3745,"lon":104.65}}]},"VTUZ":{"lat":16.6522,"lon":102.967,"elev":null,"region":"TH-40","runways":[{"len":10359,"wid":148,"surf":"CON","lit":false,"closed":false,"le":{"id":"01","hdg":7.0,"lat":16.6384,"lon":102.966},"he":{"id":"19","hdg":187.0,"lat":16.6667,"lon":102.969}}]}}